{
 "1": {
  "title": "George Washington",
  "messagesList": []
 },
 "2": {
  "title": "Pamela Anderson",
  "messagesList": []
 },
 "3": {
  "title": "Tom Cruise",
  "messagesList": []
 },
 "4": {
  "title": "фывф",
  "messagesList": []
 },
 "5": {
  "title": "фыв",
  "messagesList": []
 },
 "6": {
  "title": "фыв",
  "messagesList": []
 },
 "7": {
  "title": "фыв",
  "messagesList": []
 },
 "8": {
  "title": "фыв",
  "messagesList": []
 },
 "9": {
  "title": "фыв",
  "messagesList": []
 },
 "10": {
  "title": "фыв",
  "messagesList": []
 },
 "11": {
  "title": "фыв",
  "messagesList": []
 }
}